E03_sat_cocotb_test/hdl/sat_filter.sv
/**
////////////////////////////////////////////////////////////////////////////////////////////////////////////

- Saturation Filter:
  - This module receives a signal and filters it.
  - It can either saturate the output or pass the signal through.

/////////////////////////////////////////////////////////////////////////////////////////////////////////////
*/

module sat_filter #(
    parameter THRESHOLD = 8,   // Threshold value
    parameter DATA_W = 4       // Data signal bit size
  )
  (
    input   logic               clk,
    input   logic               rst,
    input   logic [DATA_W-1:0]  in_data,    // input data signal
    input   logic               in_valid,   // input data valid signal
    output  logic               ovf,        // overflow signal
    output  logic               out_valid,  // valid output signal
    output  logic [DATA_W-1:0]  out_data    // output signal
  );

  localparam threshold_val = THRESHOLD;

  // Generate waves files.
//  initial
//  begin
//    $dumpfile ("sim_build/sat_filter_waves.vcd");
//    $dumpvars (0, sat_filter);
//  end

  // Main loop
  always_ff @(posedge clk, posedge rst)
  begin
    if (rst === 1'b1)
    begin
      ovf <= 'b0;
      out_valid <= 'b0;
      out_data <= 'b0;
    end
    else
    begin
      if (in_valid === 1'b1)
      begin
        if (in_data > threshold_val)
        begin
          out_data <= threshold_val;
          ovf <= 'b1;
        end
        else // Valid output: (in_data <= threshold_val)
        begin
          out_data <= in_data;
          ovf <= 'b0;
        end
        out_valid <= 'b1;
      end
      else
        begin
        out_data <= 'b0;
        out_valid <= 'b0;
        ovf <= 'b0;
        end
    end
  end

endmodule

L05_Exercises/sat_filter/src/rtl/sat_filter_wrapper.sv
/**
////////////////////////////////////////////////////////////////////////////////////////////////////////////
- Saturation Filter TB

- TB module wrapping the design.

/////////////////////////////////////////////////////////////////////////////////////////////////////////////
*/

// Includes are defined in Makefile when using COCOTB
`ifndef COCOTB_SIM
  `include "sat_filter.sv"
`endif

module sat_filter_wrapper #(
    parameter THRESHOLD = 8,   // Threshold value
    parameter DATA_W = 4       // Data signal bit size
  )
  (
    // input   logic               clk,
    input   logic               rst,
    input   logic [DATA_W-1:0]  in_data,    // input data signal
    input   logic               in_valid,   // input data valid signal
    output  logic               ovf,        // overflow signal
    output  logic               out_valid,  // valid output signal
    output  logic [DATA_W-1:0]  out_data    // output signal
  );

  sat_filter #(
    .THRESHOLD(THRESHOLD), // CHANGE TO 0 FOR ROBUSTNESS TESTING
    .DATA_W(DATA_W)
  )
  sat_filter_0 (
    .clk(clk),
    .rst(rst),
    .in_data(in_data),
    .in_valid(in_valid),
    .ovf(ovf),
    .out_valid(out_valid),
    .out_data(out_data)
  );

  // Clock generation
  logic clk;
  initial
  begin
    clk <= 0;
    forever
    begin
      #2.5ns clk = ~clk;
    end
  end

endmodule

L07_Exercise/sat_filter/src/tb/sim_build/sat_filter_waves.vcd
$date
	Sun Oct 26 21:08:06 2025
$end
$version
	Icarus Verilog
$end
$timescale
	1ps
$end
$scope module sat_filter_wrapper $end
$scope module sat_filter_0 $end
$var wire 1 ! clk $end
$var wire 4 " in_data [3:0] $end
$var wire 1 # in_valid $end
$var wire 1 $ rst $end
$var parameter 32 % DATA_W $end
$var parameter 32 & THRESHOLD $end
$var parameter 32 ' threshold_val $end
$var reg 4 ( out_data [3:0] $end
$var reg 1 ) out_valid $end
$var reg 1 * ovf $end
$upscope $end
$upscope $end
$enddefinitions $end
$comment Show the parameter values. $end
$dumpall
b1000 '
b1000 &
b100 %
$end
#0
$dumpvars
x*
x)
bx (
z$
0#
b0 "
0!
$end
#2500
1$
0*
b0 (
0)
1!
#5000
0!
#7500
1!
#10000
0!
#12500
1#
0$
1!
#15000
0!
#17500
0#
1)
1!
#20000
0!
#22500
1#
b111 "
0)
1!
#25000
0!
#27500
0#
b0 "
b111 (
1)
1!
#30000
0!
#32500
1#
b101 "
b0 (
0)
1!
#35000
0!
#37500
0#
b0 "
b101 (
1)
1!
#40000
0!
#42500
1#
b1 "
b0 (
0)
1!
#45000
0!
#47500
0#
b0 "
b1 (
1)
1!
#50000
0!
#52500
1#
b1011 "
b0 (
0)
1!
#55000
0!
#57500
0#
b0 "
1*
b1000 (
1)
1!
#60000
0!
#62500
0*
b0 (
0)
1!
