E03_sat_cocotb_test/hdl/sat_filter.sv
/**
////////////////////////////////////////////////////////////////////////////////////////////////////////////

- Saturation Filter:
  - This module receives a signal and filters it.
  - It can either saturate the output or pass the signal through.

/////////////////////////////////////////////////////////////////////////////////////////////////////////////
*/

module sat_filter #(
    parameter THRESHOLD = 8,   // Threshold value
    parameter DATA_W = 4       // Data signal bit size
  )
  (
    input   logic               clk,
    input   logic               rst,
    input   logic [DATA_W-1:0]  in_data,    // input data signal
    input   logic               in_valid,   // input data valid signal
    output  logic               ovf,        // overflow signal
    output  logic               out_valid,  // valid output signal
    output  logic [DATA_W-1:0]  out_data    // output signal
  );

  localparam threshold_val = THRESHOLD;

  // Generate waves files.
//  initial
//  begin
//    $dumpfile ("sim_build/sat_filter_waves.vcd");
//    $dumpvars (0, sat_filter);
//  end

  // Main loop
  always_ff @(posedge clk, posedge rst)
  begin
    if (rst === 1'b1)
    begin
      ovf <= 'b0;
      out_valid <= 'b0;
      out_data <= 'b0;
    end
    else
    begin
      if (in_valid === 1'b1)
      begin
        if (in_data > threshold_val)
        begin
          out_data <= threshold_val;
          ovf <= 'b1;
        end
        else // Valid output: (in_data <= threshold_val)
        begin
          out_data <= in_data;
          ovf <= 'b0;
        end
        out_valid <= 'b1;
      end
      else
        begin
        out_data <= 'b0;
        out_valid <= 'b0;
        ovf <= 'b0;
        end
    end
  end

endmodule

L05_Exercises/sat_filter/src/rtl/sat_filter_wrapper.sv
/**
////////////////////////////////////////////////////////////////////////////////////////////////////////////
- Saturation Filter TB

- TB module wrapping the design.

/////////////////////////////////////////////////////////////////////////////////////////////////////////////
*/

// Includes are defined in Makefile when using COCOTB
`ifndef COCOTB_SIM
  `include "sat_filter.sv"
`endif

module sat_filter_wrapper #(
    parameter THRESHOLD = 8,   // Threshold value
    parameter DATA_W = 4       // Data signal bit size
  )
  (
    // input   logic               clk,
    input   logic               rst,
    input   logic [DATA_W-1:0]  in_data,    // input data signal
    input   logic               in_valid,   // input data valid signal
    output  logic               ovf,        // overflow signal
    output  logic               out_valid,  // valid output signal
    output  logic [DATA_W-1:0]  out_data    // output signal
  );

  sat_filter #(
    .THRESHOLD(THRESHOLD), // CHANGE TO 0 FOR ROBUSTNESS TESTING
    .DATA_W(DATA_W)
  )
  sat_filter_0 (
    .clk(clk),
    .rst(rst),
    .in_data(in_data),
    .in_valid(in_valid),
    .ovf(ovf),
    .out_valid(out_valid),
    .out_data(out_data)
  );

  // Clock generation
  logic clk;
  initial
  begin
    clk <= 0;
    forever
    begin
      #2.5ns clk = ~clk;
    end
  end

endmodule

L06_Exercises/sat_filter/src/tb/sim_build/sat_filter_waves.vcd
$date
	Mon Oct  6 11:18:29 2025
$end
$version
	Icarus Verilog
$end
$timescale
	1ps
$end
$scope module sat_filter_wrapper $end
$scope module sat_filter_0 $end
$var wire 1 ! clk $end
$var wire 4 " in_data [3:0] $end
$var wire 1 # in_valid $end
$var wire 1 $ rst $end
$var parameter 32 % DATA_W $end
$var parameter 32 & THRESHOLD $end
$var parameter 32 ' threshold_val $end
$var reg 4 ( out_data [3:0] $end
$var reg 1 ) out_valid $end
$var reg 1 * ovf $end
$upscope $end
$upscope $end
$enddefinitions $end
$comment Show the parameter values. $end
$dumpall
b1000 '
b1000 &
b100 %
$end
#0
$dumpvars
x*
x)
bx (
z$
0#
b0 "
0!
$end
#2500
1$
0*
b0 (
0)
1!
#5000
0!
#7500
1!
#10000
0!
#12500
1#
b101 "
0$
1!
#15000
0!
#17500
0#
b0 "
b101 (
1)
1!
#20000
0!
#22500
1#
b1001 "
b0 (
0)
1!
#25000
0!
#27500
0#
b0 "
1*
b1000 (
1)
1!
#30000
0!
#32500
1#
b1010 "
0*
b0 (
0)
1!
#35000
0!
#37500
0#
b0 "
1*
b1000 (
1)
1!
#40000
0!
#42500
1#
b1011 "
0*
b0 (
0)
1!
#45000
0!
#47500
0#
b0 "
1*
b1000 (
1)
1!
#50000
0!
#52500
1#
b110 "
0*
b0 (
0)
1!
#55000
0!
#57500
0#
b0 "
b110 (
1)
1!
#60000
0!
#62500
b0 (
0)
1!
#65000
0!
#67500
1$
1!
#70000
0!
#72500
1!
#75000
0!
#77500
1#
b1011 "
0$
1!
#80000
0!
#82500
0#
b0 "
1*
b1000 (
1)
1!
#85000
0!
#87500
1#
b1111 "
0*
b0 (
0)
1!
#90000
0!
#92500
0#
b0 "
1*
b1000 (
1)
1!
#95000
0!
#97500
1#
0*
b0 (
0)
1!
#100000
0!
#102500
0#
1)
1!
#105000
0!
#107500
1#
b11 "
0)
1!
#110000
0!
#112500
0#
b0 "
b11 (
1)
1!
#115000
0!
#117500
1#
b1100 "
b0 (
0)
1!
#120000
0!
#122500
0#
b0 "
1*
b1000 (
1)
1!
#125000
0!
#127500
1#
b10 "
0*
b0 (
0)
1!
#130000
0!
#132500
0#
b0 "
b10 (
1)
1!
#135000
0!
#137500
1#
b1100 "
b0 (
0)
1!
#140000
0!
#142500
0#
b0 "
1*
b1000 (
1)
1!
#145000
0!
#147500
1#
b1101 "
0*
b0 (
0)
1!
#150000
0!
#152500
0#
b0 "
1*
b1000 (
1)
1!
#155000
0!
#157500
1#
b111 "
0*
b0 (
0)
1!
#160000
0!
#162500
0#
b0 "
b111 (
1)
1!
#165000
0!
#167500
1#
b1011 "
b0 (
0)
1!
#170000
0!
#172500
0#
b0 "
1*
b1000 (
1)
1!
#175000
0!
#177500
1#
b111 "
0*
b0 (
0)
1!
#180000
0!
#182500
0#
b0 "
b111 (
1)
1!
#185000
0!
#187500
1#
b1001 "
b0 (
0)
1!
#190000
0!
#192500
0#
b0 "
1*
b1000 (
1)
1!
#195000
0!
#197500
1#
b1001 "
0*
b0 (
0)
1!
#200000
0!
#202500
0#
b0 "
1*
b1000 (
1)
1!
#205000
0!
#207500
1#
0*
b0 (
0)
1!
#210000
0!
#212500
0#
1)
1!
#215000
0!
#217500
1#
b1111 "
0)
1!
#220000
0!
#222500
0#
b0 "
1*
b1000 (
1)
1!
#225000
0!
#227500
1#
b1010 "
0*
b0 (
0)
1!
#230000
0!
#232500
0#
b0 "
1*
b1000 (
1)
1!
#235000
0!
#237500
1#
b10 "
0*
b0 (
0)
1!
#240000
0!
#242500
0#
b0 "
b10 (
1)
1!
#245000
0!
#247500
1#
b11 "
b0 (
0)
1!
#250000
0!
#252500
0#
b0 "
b11 (
1)
1!
#255000
0!
#257500
1#
b1 "
b0 (
0)
1!
#260000
0!
#262500
0#
b0 "
b1 (
1)
1!
#265000
0!
#267500
1#
b10 "
b0 (
0)
1!
#270000
0!
#272500
0#
b0 "
b10 (
1)
1!
#275000
0!
#277500
1#
b1010 "
b0 (
0)
1!
#280000
0!
#282500
0#
b0 "
1*
b1000 (
1)
1!
#285000
0!
#287500
1#
b111 "
0*
b0 (
0)
1!
#290000
0!
#292500
0#
b0 "
b111 (
1)
1!
#295000
0!
#297500
1#
b1 "
b0 (
0)
1!
#300000
0!
#302500
0#
b0 "
b1 (
1)
1!
#305000
0!
#307500
1#
b1101 "
b0 (
0)
1!
#310000
0!
#312500
0#
b0 "
1*
b1000 (
1)
1!
#315000
0!
#317500
1#
b1011 "
0*
b0 (
0)
1!
#320000
0!
#322500
0#
b0 "
1*
b1000 (
1)
1!
#325000
0!
#327500
1#
b1110 "
0*
b0 (
0)
1!
#330000
0!
#332500
0#
b0 "
1*
b1000 (
1)
1!
#335000
0!
#337500
1#
b1100 "
0*
b0 (
0)
1!
#340000
0!
#342500
0#
b0 "
1*
b1000 (
1)
1!
#345000
0!
#347500
1#
b1000 "
0*
b0 (
0)
1!
#350000
0!
#352500
0#
b0 "
b1000 (
1)
1!
#355000
0!
#357500
1#
b1011 "
b0 (
0)
1!
#360000
0!
#362500
0#
b0 "
1*
b1000 (
1)
1!
#365000
0!
#367500
1#
b1100 "
0*
b0 (
0)
1!
#370000
0!
#372500
0#
b0 "
1*
b1000 (
1)
1!
#375000
0!
#377500
1#
b1101 "
0*
b0 (
0)
1!
#380000
0!
#382500
0#
b0 "
1*
b1000 (
1)
1!
#385000
0!
#387500
1#
b1001 "
0*
b0 (
0)
1!
#390000
0!
#392500
0#
b0 "
1*
b1000 (
1)
1!
#395000
0!
#397500
1#
b1111 "
0*
b0 (
0)
1!
#400000
0!
#402500
0#
b0 "
1*
b1000 (
1)
1!
#405000
0!
#407500
1#
b110 "
0*
b0 (
0)
1!
#410000
0!
#412500
0#
b0 "
b110 (
1)
1!
#415000
0!
#417500
1#
b1110 "
b0 (
0)
1!
#420000
0!
#422500
0#
b0 "
1*
b1000 (
1)
1!
#425000
0!
#427500
1#
b1100 "
0*
b0 (
0)
1!
#430000
0!
#432500
0#
b0 "
1*
b1000 (
1)
1!
#435000
0!
#437500
1#
0*
b0 (
0)
1!
#440000
0!
#442500
0#
1)
1!
#445000
0!
#447500
1#
b10 "
0)
1!
#450000
0!
#452500
0#
b0 "
b10 (
1)
1!
#455000
0!
#457500
1#
b1100 "
b0 (
0)
1!
#460000
0!
#462500
0#
b0 "
1*
b1000 (
1)
1!
#465000
0!
#467500
1#
b100 "
0*
b0 (
0)
1!
#470000
0!
#472500
0#
b0 "
b100 (
1)
1!
#475000
0!
#477500
1#
b1101 "
b0 (
0)
1!
#480000
0!
#482500
0#
b0 "
1*
b1000 (
1)
1!
#485000
0!
#487500
1#
b1 "
0*
b0 (
0)
1!
#490000
0!
#492500
0#
b0 "
b1 (
1)
1!
#495000
0!
#497500
1#
b1 "
b0 (
0)
1!
#500000
0!
#502500
0#
b0 "
b1 (
1)
1!
#505000
0!
#507500
1#
b1011 "
b0 (
0)
1!
#510000
0!
#512500
0#
b0 "
1*
b1000 (
1)
1!
#515000
0!
#517500
1#
b1 "
0*
b0 (
0)
1!
#520000
0!
#522500
0#
b0 "
b1 (
1)
1!
#525000
0!
#527500
1#
b100 "
b0 (
0)
1!
#530000
0!
#532500
0#
b0 "
b100 (
1)
1!
#535000
0!
#537500
1#
b110 "
b0 (
0)
1!
#540000
0!
#542500
0#
b0 "
b110 (
1)
1!
#545000
0!
#547500
1#
b110 "
b0 (
0)
1!
#550000
0!
#552500
0#
b0 "
b110 (
1)
1!
#555000
0!
#557500
1#
b101 "
b0 (
0)
1!
#560000
0!
#562500
0#
b0 "
b101 (
1)
1!
#565000
0!
#567500
1#
b1101 "
b0 (
0)
1!
#570000
0!
#572500
0#
b0 "
1*
b1000 (
1)
1!
#575000
0!
#577500
1#
b101 "
0*
b0 (
0)
1!
#580000
0!
#582500
0#
b0 "
b101 (
1)
1!
#585000
0!
#587500
1#
b1100 "
b0 (
0)
1!
#590000
0!
#592500
0#
b0 "
1*
b1000 (
1)
1!
#595000
0!
#597500
1#
b101 "
0*
b0 (
0)
1!
#600000
0!
#602500
0#
b0 "
b101 (
1)
1!
#605000
0!
#607500
1#
b1110 "
b0 (
0)
1!
#610000
0!
#612500
0#
b0 "
1*
b1000 (
1)
1!
#615000
0!
#617500
1#
b110 "
0*
b0 (
0)
1!
#620000
0!
#622500
0#
b0 "
b110 (
1)
1!
#625000
0!
#627500
1#
b1011 "
b0 (
0)
1!
#630000
0!
#632500
0#
b0 "
1*
b1000 (
1)
1!
#635000
0!
#637500
1#
b1101 "
0*
b0 (
0)
1!
#640000
0!
#642500
0#
b0 "
1*
b1000 (
1)
1!
#645000
0!
#647500
1#
b11 "
0*
b0 (
0)
1!
#650000
0!
#652500
0#
b0 "
b11 (
1)
1!
#655000
0!
#657500
1#
b1000 "
b0 (
0)
1!
#660000
0!
#662500
0#
b0 "
b1000 (
1)
1!
#665000
0!
#667500
1#
b100 "
b0 (
0)
1!
#670000
0!
#672500
0#
b0 "
b100 (
1)
1!
#675000
0!
#677500
1#
b111 "
b0 (
0)
1!
#680000
0!
#682500
0#
b0 "
b111 (
1)
1!
#685000
0!
#687500
1#
b1011 "
b0 (
0)
1!
#690000
0!
#692500
0#
b0 "
1*
b1000 (
1)
1!
#695000
0!
#697500
1#
b1 "
0*
b0 (
0)
1!
#700000
0!
#702500
0#
b0 "
b1 (
1)
1!
#705000
0!
#707500
1#
b1000 "
b0 (
0)
1!
#710000
0!
#712500
0#
b0 "
b1000 (
1)
1!
#715000
0!
#717500
1#
b0 (
0)
1!
#720000
0!
#722500
0#
1)
1!
#725000
0!
#727500
1#
b11 "
0)
1!
#730000
0!
#732500
0#
b0 "
b11 (
1)
1!
#735000
0!
#737500
1#
b1 "
b0 (
0)
1!
#740000
0!
#742500
0#
b0 "
b1 (
1)
1!
#745000
0!
#747500
1#
b100 "
b0 (
0)
1!
#750000
0!
#752500
0#
b0 "
b100 (
1)
1!
#755000
0!
#757500
1#
b100 "
b0 (
0)
1!
#760000
0!
#762500
0#
b0 "
b100 (
1)
1!
#765000
0!
#767500
1#
b1101 "
b0 (
0)
1!
#770000
0!
#772500
0#
b0 "
1*
b1000 (
1)
1!
#775000
0!
#777500
1#
b1001 "
0*
b0 (
0)
1!
#780000
0!
#782500
0#
b0 "
1*
b1000 (
1)
1!
#785000
0!
#787500
1#
b1001 "
0*
b0 (
0)
1!
#790000
0!
#792500
0#
b0 "
1*
b1000 (
1)
1!
#795000
0!
#797500
1#
b10 "
0*
b0 (
0)
1!
#800000
0!
#802500
0#
b0 "
b10 (
1)
1!
#805000
0!
#807500
1#
b0 (
0)
1!
#810000
0!
#812500
0#
1)
1!
#815000
0!
#817500
1#
b1100 "
0)
1!
#820000
0!
#822500
0#
b0 "
1*
b1000 (
1)
1!
#825000
0!
#827500
1#
b111 "
0*
b0 (
0)
1!
#830000
0!
#832500
0#
b0 "
b111 (
1)
1!
#835000
0!
#837500
1#
b10 "
b0 (
0)
1!
#840000
0!
#842500
0#
b0 "
b10 (
1)
1!
#845000
0!
#847500
1#
b0 (
0)
1!
#850000
0!
#852500
0#
1)
1!
#855000
0!
#857500
1#
b11 "
0)
1!
#860000
0!
#862500
0#
b0 "
b11 (
1)
1!
#865000
0!
#867500
b0 (
0)
1!
